jmawirat_ml_helpers/__init__.py
jmawirat_ml_helpers/data_split.py
jmawirat_ml_helpers/feature_engineering.py
jmawirat_ml_helpers/stationarity.py
jmawirat_ml_helpers-1.0.3.dist-info/METADATA
jmawirat_ml_helpers-1.0.3.dist-info/WHEEL
jmawirat_ml_helpers-1.0.3.dist-info/top_level.txt
jmawirat_ml_helpers-1.0.3.dist-info/RECORD
