Metadata-Version: 2.2
Name: jmawirat_ml_helpers
Version: 1.0.3
Summary: Time-series data splitting, feature engineering, and stationarity transformations
Home-page: https://github.com/jonelmawirat/ml_helpers
Author: Jonel Mawirat
Author-email: jmawirat@outlook.com
License: MIT
Keywords: time-series splitting feature-engineering stationarity machine-learning
Classifier: Programming Language :: Python :: 3
Classifier: Operating System :: OS Independent
Classifier: License :: OSI Approved :: MIT License
Requires-Python: >=3.7
Requires-Dist: numpy>=1.18.0
Requires-Dist: pandas>=1.0.0
Requires-Dist: matplotlib>=3.0.0
Requires-Dist: statsmodels>=0.12.0
Dynamic: author
Dynamic: author-email
Dynamic: classifier
Dynamic: description
Dynamic: description-content-type
Dynamic: home-page
Dynamic: keywords
Dynamic: license
Dynamic: requires-dist
Dynamic: requires-python
Dynamic: summary
